fermentools/__init__.py
fermentools/chemometrics/__init__.py
fermentools/chemometrics/modelling/__init__.py
fermentools/chemometrics/modelling/cross_validation.py
fermentools/chemometrics/models/__init__.py
fermentools/chemometrics/models/load_pls_glucose_model.py
fermentools/chemometrics/preprocessing/__init__.py
fermentools/chemometrics/preprocessing/preprocessing.py
fermentools/datasets/__init__.py
fermentools/datasets/fluorescence/__init__.py
fermentools/datasets/fluorescence/_base.py
fermentools/datasets/fluorescence/data/__init__.py
fermentools/datasets/ir/__init__.py
fermentools/datasets/ir/_base.py
fermentools/datasets/ir/data/__init__.py
fermentools/mechanistic/__init__.py
fermentools/mechanistic/mass_balance.py
fermentools/mechanistic/yeast_model.py
fermentools/plotting/__init__.py
fermentools/plotting/plot_chemometrics.py
fermentools/plotting/plot_mechanistic.py
fermentools/realtime/__init__.py
tests/__init__.py
tests/test_loadings.py
tests/test_preprocessing.py
fermentools-0.1.5.dist-info/LICENSE
fermentools-0.1.5.dist-info/METADATA
fermentools-0.1.5.dist-info/WHEEL
fermentools-0.1.5.dist-info/top_level.txt
fermentools-0.1.5.dist-info/RECORD
